auth_component/__init__.py
auth_component/exceptions.py
auth_component/simple_auth.py
tokenix_auth_component-0.1.4.dist-info/licenses/LICENSE
tokenix_auth_component-0.1.4.dist-info/METADATA
tokenix_auth_component-0.1.4.dist-info/WHEEL
tokenix_auth_component-0.1.4.dist-info/top_level.txt
tokenix_auth_component-0.1.4.dist-info/RECORD
